{
  "_doc": "Commander Legends (CMR) booster recipes. The `draft` block is generated by scripts/gen-booster-contents.mjs from data/_collation-facts/cmr.json (source: The Collation Project, lethe.xyz/mtg/collation) — do not hand-edit it unless you also remove its facts source. The `collector` block is authored from Wizards' official 'Collecting Commander Legends' article (magic.wizards.com/en/news/feature/collecting-commander-legends-2020-10-26); slot structure and the stated chase odds (~30% foil rare/mythic extended-art upgrade, ~20% foil uncommon extended-art upgrade) are verbatim. Per-slot rare:mythic splits are not published by Wizards, so the standard 86:14 ratio (matching the draft block) is used. Set composition: 141C / 120U / 77R / 22M. Notes: Extra-large Commander draft set with 20-card draft boosters (2 legendary slots) and a guaranteed foil. One card of special rarity (The Prismatic Piper). Foil-etched legendary reprints appear in the collector booster.",
  "authoritative": true,
  "draft": {
    "cardCount": 18,
    "tagline": "13 commons · 3 uncommons · 1× rare/mythic · 1 guaranteed foil",
    "slots": [
      {
        "label": "Common",
        "count": 13,
        "outcomes": [
          {
            "weight": 1,
            "rarity": "common"
          }
        ]
      },
      {
        "label": "Uncommon",
        "count": 3,
        "outcomes": [
          {
            "weight": 1,
            "rarity": "uncommon"
          }
        ]
      },
      {
        "label": "Rare / Mythic",
        "outcomes": [
          {
            "weight": 86,
            "rarity": "rare"
          },
          {
            "weight": 14,
            "rarity": "mythic"
          }
        ]
      },
      {
        "label": "Foil",
        "foil": true,
        "outcomes": [
          {
            "weight": 67,
            "rarity": "common",
            "foil": true
          },
          {
            "weight": 20,
            "rarity": "uncommon",
            "foil": true
          },
          {
            "weight": 10,
            "rarity": "rare",
            "foil": true
          },
          {
            "weight": 3,
            "rarity": "mythic",
            "foil": true
          }
        ]
      }
    ]
  },
  "collector": {
    "cardCount": 16,
    "tagline": "15 premium cards · 3 foil-etched legends · extended-art & foil chase slots · 1 token",
    "slots": [
      {
        "label": "Foil Common",
        "count": 5,
        "foil": true,
        "outcomes": [{ "weight": 1, "rarity": "common", "foil": true }]
      },
      {
        "label": "Foil Legendary",
        "count": 2,
        "foil": true,
        "outcomes": [
          { "weight": 80, "rarity": "uncommon", "foil": true },
          { "weight": 17, "rarity": "rare", "foil": true },
          { "weight": 3, "rarity": "mythic", "foil": true }
        ]
      },
      {
        "label": "Foil Rare / Mythic (nonlegendary)",
        "foil": true,
        "outcomes": [
          { "weight": 60.2, "rarity": "rare", "foil": true },
          { "weight": 9.8, "rarity": "mythic", "foil": true },
          { "weight": 25.8, "rarity": "rare", "foil": true, "filter": "extended_art", "label": "Extended Art" },
          { "weight": 4.2, "rarity": "mythic", "foil": true, "filter": "extended_art", "label": "Extended Art" }
        ]
      },
      {
        "label": "Extended-Art Common / Uncommon",
        "outcomes": [
          { "weight": 1, "rarity": "common", "filter": "extended_art" },
          { "weight": 1, "rarity": "uncommon", "filter": "extended_art" }
        ]
      },
      {
        "label": "Extended-Art Rare / Mythic",
        "outcomes": [
          { "weight": 86, "rarity": "rare", "filter": "extended_art" },
          { "weight": 14, "rarity": "mythic", "filter": "extended_art" }
        ]
      },
      {
        "label": "Foil Uncommon (nonlegendary)",
        "count": 2,
        "foil": true,
        "outcomes": [
          { "weight": 80, "rarity": "uncommon", "foil": true },
          { "weight": 20, "rarity": "uncommon", "foil": true, "filter": "extended_art", "label": "Extended Art" }
        ]
      },
      {
        "label": "Foil-Etched Uncommon Legendary",
        "outcomes": [{ "weight": 1, "rarity": "uncommon", "filter": "etched_foil" }]
      },
      {
        "label": "Foil-Etched Reprint Legendary",
        "outcomes": [{ "weight": 1, "rarity": "mythic", "filter": "etched_foil" }]
      },
      {
        "label": "Foil-Etched Rare / Mythic Legendary or Borderless Planeswalker",
        "outcomes": [
          { "weight": 86, "rarity": "rare", "filter": "etched_foil" },
          { "weight": 11, "rarity": "mythic", "filter": "etched_foil" },
          { "weight": 3, "rarity": "mythic", "foil": true, "filter": "borderless", "label": "Borderless Planeswalker" }
        ]
      },
      {
        "label": "Foil Double-Sided Token",
        "token": true,
        "outcomes": [{ "weight": 1, "foil": true }]
      }
    ]
  }
}
